<?xml version="1.0" encoding="utf-8" ?><dwsync><file name="about_me.html" server="hermes.waketech.edu/public_html/" local="3762970277" remote="3762970314" Dst="-1" /><file name="porfolio.html" server="hermes.waketech.edu/public_html/" local="3762977321" remote="3762977345" Dst="-1" /><file name="striped_styles.css" server="hermes.waketech.edu/public_html/" local="3762362167" remote="3762365799" Dst="-1" /><file name="style.css" server="hermes.waketech.edu/public_html/" local="3762981690" remote="3762981719" Dst="-1" /><file name="the_landing_page.html" server="hermes.waketech.edu/public_html/" local="3762981664" remote="3762981666" Dst="-1" /><file name="contact.html" server="hermes.waketech.edu/public_html/" local="3762981545" remote="3762981601" Dst="-1" /><file name="test.html" server="hermes.waketech.edu/public_html/" local="3762931166" remote="3762965900" Dst="-1" /><file name="blogs.html" server="hermes.waketech.edu/public_html/" local="3762977347" remote="3762977345" Dst="-1" /></dwsync>